nfractal/__init__.py
nfractal/colorize.py
nfractal/nn.py
nfractal/samplers.py
nfractal/utils/__init__.py
nfractal/utils/colorspace.py
nfractal/utils/dev.py
nfractal/utils/enhancements.py
nfractal-0.3.0.dist-info/LICENSE
nfractal-0.3.0.dist-info/METADATA
nfractal-0.3.0.dist-info/WHEEL
nfractal-0.3.0.dist-info/top_level.txt
nfractal-0.3.0.dist-info/RECORD
