Metadata-Version: 2.1
Name: nfractal
Version: 0.3.0
Summary: Create Fractals Using Complex-Valued Neural Networks!
Home-page: https://github.com/amirabbasasadi/neural-fractal.git
Author: Amirabbas Asadi
Author-email: amir137825@gmail.com
License: UNKNOWN
Platform: UNKNOWN
Requires-Dist: tqdm
Requires-Dist: torch (>=1.8.1)
